Metadata-Version: 1.0
Name: dashgrid
Version: 0.0.1
Summary: Dash UI component suite
Home-page: UNKNOWN
Author: UNKNOWN
Author-email: UNKNOWN
License: MIT
Platform: UNKNOWN
